{"assets/.DS_Store":["assets/.DS_Store"],"assets/.env":["assets/.env"],"assets/env.development":["assets/env.development"],"assets/env.production":["assets/env.production"],"assets/images/.DS_Store":["assets/images/.DS_Store"],"assets/images/10681Insight.jpeg":["assets/images/10681Insight.jpeg"],"assets/images/cauhoi/.DS_Store":["assets/images/cauhoi/.DS_Store"],"assets/images/cauhoi/ch01.1Hoa.png":["assets/images/cauhoi/ch01.1Hoa.png"],"assets/images/cauhoi/ch01.2Kim.png":["assets/images/cauhoi/ch01.2Kim.png"],"assets/images/cauhoi/ch01.3Moc.png":["assets/images/cauhoi/ch01.3Moc.png"],"assets/images/cauhoi/ch01.4Tho.png":["assets/images/cauhoi/ch01.4Tho.png"],"assets/images/cauhoi/ch11lm.1.png":["assets/images/cauhoi/ch11lm.1.png"],"assets/images/cauhoi/ch11lm.2.png":["assets/images/cauhoi/ch11lm.2.png"],"assets/images/cauhoi/ch11lm.3.png":["assets/images/cauhoi/ch11lm.3.png"],"assets/images/cauhoi/ch11lm.4.png":["assets/images/cauhoi/ch11lm.4.png"],"assets/images/cauhoi/ch12lm.kdkn.png":["assets/images/cauhoi/ch12lm.kdkn.png"],"assets/images/cauhoi/ch12lm.ratdam.png":["assets/images/cauhoi/ch12lm.ratdam.png"],"assets/images/cauhoi/ch12lm.ratnhat.png":["assets/images/cauhoi/ch12lm.ratnhat.png"],"assets/images/cauhoi/ch13.dmlc.png":["assets/images/cauhoi/ch13.dmlc.png"],"assets/images/cauhoi/ch13.dmngang.png":["assets/images/cauhoi/ch13.dmngang.png"],"assets/images/cauhoi/ch13.dmxt.png":["assets/images/cauhoi/ch13.dmxt.png"],"assets/images/cauhoi/ch14.matnho.png":["assets/images/cauhoi/ch14.matnho.png"],"assets/images/cauhoi/ch14.matto.png":["assets/images/cauhoi/ch14.matto.png"],"assets/images/cauhoi/ch15.muicaogk.png":["assets/images/cauhoi/ch15.muicaogk.png"],"assets/images/cauhoi/ch15.muict.png":["assets/images/cauhoi/ch15.muict.png"],"assets/images/cauhoi/ct15.muithap.png":["assets/images/cauhoi/ct15.muithap.png"],"assets/images/insight_lt.png":["assets/images/insight_lt.png"],"packages/cupertino_icons/assets/CupertinoIcons.ttf":["packages/cupertino_icons/assets/CupertinoIcons.ttf"],"packages/fluttertoast/assets/toastify.css":["packages/fluttertoast/assets/toastify.css"],"packages/fluttertoast/assets/toastify.js":["packages/fluttertoast/assets/toastify.js"]}